WrappedLLM/GPTFunctions.py
WrappedLLM/LLMInitialization.py
WrappedLLM/LLMModels.py
WrappedLLM/LLMOutput.py
WrappedLLM/README.md
WrappedLLM/__init__.py
WrappedLLM-0.1.9.7.dist-info/LICENSE
WrappedLLM-0.1.9.7.dist-info/METADATA
WrappedLLM-0.1.9.7.dist-info/WHEEL
WrappedLLM-0.1.9.7.dist-info/top_level.txt
WrappedLLM-0.1.9.7.dist-info/RECORD
