Metadata-Version: 2.1
Name: WrappedLLM
Version: 0.1.9.7
Summary: A wrapper for various large language models including GPT, Claude, and Gemini
Home-page: https://github.com/JayceeGupta/WrappedLLM
Author: Jayam Gupta
Author-email: guptajayam47@gmail.com
Classifier: Programming Language :: Python :: 3
Classifier: License :: OSI Approved :: MIT License
Classifier: Operating System :: OS Independent
Requires-Python: >=3.7
License-File: LICENSE
Requires-Dist: openai >=1.66.3
Requires-Dist: anthropic
Requires-Dist: google-generativeai
Requires-Dist: pydantic
